actions_runner/__init__.py
actions_runner/main.py
actions_runner-0.0.1.dist-info/METADATA
actions_runner-0.0.1.dist-info/WHEEL
actions_runner-0.0.1.dist-info/licenses/LICENSE
actions_runner-0.0.1.dist-info/RECORD
