Metadata-Version: 2.4
Name: actions-runner
Version: 0.0.1
Summary: Run GitHub Actions workflows locally in Python. Powered by `act` (nektosact.com).
Author-email: AJ Steers <aaronsteers@example.com>
License-Expression: MIT
License-File: LICENSE
Requires-Python: >=3.11
Provides-Extra: dev
Requires-Dist: build; extra == 'dev'
Requires-Dist: twine; extra == 'dev'
